README.md
setup.cfg
setup.py
chance_config.egg-info/PKG-INFO
chance_config.egg-info/SOURCES.txt
chance_config.egg-info/dependency_links.txt
chance_config.egg-info/not-zip-safe
chance_config.egg-info/requires.txt
chance_config.egg-info/top_level.txt
chanconfig/__init__.py
chanconfig/config.py
chanconfig/multiple_config.py
chanconfig/utils.py