Metadata-Version: 1.0
Name: chance-config
Version: 0.0.8
Summary: The config for chancefocus
Home-page: https://gitee.com/QianFuFinancial/config.git
Author: Jimin Huang
Author-email: jimin@chancefocus.com
License: MIT
Platform: UNKNOWN
